MANIFEST.in
README.md
lgpl-2.1.txt
setup.cfg
setup.py
pylirious/__init__.py
pylirious/bpylirious.py
pylirious/filename.py
pylirious/mmlirious.py
pylirious/pylirious.py
pylirious/setup_exe_paths.py
pylirious/write_bpy.py
pylirious/write_mmpy.py
pylirious.egg-info/PKG-INFO
pylirious.egg-info/SOURCES.txt
pylirious.egg-info/dependency_links.txt
pylirious.egg-info/requires.txt
pylirious.egg-info/top_level.txt
pylirious/mm-api/.git
pylirious/mm-api/.gitignore
pylirious/mm-api/LICENSE
pylirious/mm-api/README.md
pylirious/mm-api/build_csharp_distrib.bat
pylirious/mm-api/build_csharp_distrib_unity.bat
pylirious/mm-api/build_python_distrib.bat
pylirious/mm-api/build_python_distrib.sh
pylirious/mm-api/build/BinarySerializer.h
pylirious/mm-api/build/INSTRUCTIONS.txt
pylirious/mm-api/build/LiveMesh.cpp
pylirious/mm-api/build/LiveMesh.h
pylirious/mm-api/build/StoredCommands.cpp
pylirious/mm-api/build/StoredCommands.h
pylirious/mm-api/build/build_csharp_VS2012.bat
pylirious/mm-api/build/build_csharp_VS2012_unity.bat
pylirious/mm-api/build/build_python_VS2012.bat
pylirious/mm-api/build/build_python_osx.sh
pylirious/mm-api/build/install_swig_osx.sh
pylirious/mm-api/build/lgConfig.h
pylirious/mm-api/build/lgConfig_osx.h
pylirious/mm-api/build/make_package_cpp.bat
pylirious/mm-api/build/make_package_csharp.bat
pylirious/mm-api/build/make_package_csharp_unity.bat
pylirious/mm-api/build/make_package_python.bat
pylirious/mm-api/build/make_package_python.sh
pylirious/mm-api/build/mmAPI.i
pylirious/mm-api/build/mmRemote.py
pylirious/mm-api/build/setup.py
pylirious/mm-api/build/stdafx.h
pylirious/mm-api/build/test.py
pylirious/mm-api/build/csharp_vsproj_files/AssemblyInfo.cs
pylirious/mm-api/build/csharp_vsproj_files/Program.cs
pylirious/mm-api/build/csharp_vsproj_files/RemoteControl.cs
pylirious/mm-api/build/csharp_vsproj_files/mmapi_cpp_dll.vcxproj
pylirious/mm-api/build/csharp_vsproj_files/mmapi_csharp.csproj
pylirious/mm-api/build/csharp_vsproj_files/mmapi_csharp.sln
pylirious/mm-api/build/csharp_vsproj_files/mmapi_planecut_test.csproj
pylirious/mm-api/build/csharp_vsproj_files_unity/AssemblyInfo.cs
