Metadata-Version: 1.0
Name: pylirious
Version: 20160916
Summary: 3D model creation and processing with Python
Home-page: https://github.com/3DLIRIOUS/pylirious
Author: 3DLirious
Author-email: 3DLirious@gmail.com
License: LGPL-2.1
Platform: UNKNOWN
